gitea/__init__.py
gitea/apiobject.py
gitea/baseapiobject.py
gitea/exceptions.py
gitea/gitea.py
py_gitea-0.2.10.dist-info/licenses/LICENSE
py_gitea-0.2.10.dist-info/METADATA
py_gitea-0.2.10.dist-info/WHEEL
py_gitea-0.2.10.dist-info/top_level.txt
py_gitea-0.2.10.dist-info/RECORD
