Metadata-Version: 2.4
Name: py-gitea
Version: 0.2.10
Summary: A python wrapper for the Gitea API
Author-email: Vincent Langenfeld <langenfv@informatik.uni-freiburg.de>
License-Expression: MIT
Keywords: Gitea,api,wrapper
Requires-Python: >=3.11
License-File: LICENSE
Requires-Dist: requests
Requires-Dist: immutabledict
Dynamic: license-file
